PADAWAN_helper/__init__.py
PADAWAN_helper/addressbook.py
PADAWAN_helper/menu.py
PADAWAN_helper/notebook.py
PADAWAN_helper/sort.py
PADAWAN_helper-0.0.6.dist-info/LICENSE
PADAWAN_helper-0.0.6.dist-info/METADATA
PADAWAN_helper-0.0.6.dist-info/WHEEL
PADAWAN_helper-0.0.6.dist-info/entry_points.txt
PADAWAN_helper-0.0.6.dist-info/top_level.txt
PADAWAN_helper-0.0.6.dist-info/RECORD
